bmkginfo/__init__.py
bmkginfo-0.0.7.dist-info/LICENSE
bmkginfo-0.0.7.dist-info/METADATA
bmkginfo-0.0.7.dist-info/WHEEL
bmkginfo-0.0.7.dist-info/top_level.txt
bmkginfo-0.0.7.dist-info/RECORD
