Metadata-Version: 2.1
Name: bmkginfo
Version: 0.0.7
Summary: BMKGINFO is a Python library for getting information about latest earth quake and wheather forecast in Indonesia base on BMKG | Meteorological, Climatological, and Geophysical Agency Website.
Home-page: https://github.com/endang-ismaya/bmkginfo
Author: Endang Ismaya
Author-email: endang.ismaya@gmail.com
License: UNKNOWN
Project-URL: Bug Tracker, https://github.com/endang-ismaya/bmkginfo/issues
Platform: UNKNOWN
Classifier: Programming Language :: Python :: 3
Classifier: License :: OSI Approved :: MIT License
Classifier: Operating System :: OS Independent
Classifier: Development Status :: 5 - Production/Stable
Requires-Python: >=3.6
License-File: LICENSE
Requires-Dist: requests
Requires-Dist: beautifulsoup4
